ai4flwr/__init__.py
ai4flwr/auth/__init__.py
ai4flwr/auth/bearer.py
ai4flwr-0.2.0.dist-info/LICENSE
ai4flwr-0.2.0.dist-info/METADATA
ai4flwr-0.2.0.dist-info/WHEEL
ai4flwr-0.2.0.dist-info/RECORD
