Metadata-Version: 2.1
Name: ai4flwr
Version: 0.2.0
Summary: AI4OS extensions to the Python Flower federated learning framework (https://flower.dev)
License: GPL-3
Author: Alvaro Lopez Garcia
Author-email: aloga@ifca.unican.es
Requires-Python: >=3.10,<4.0
Classifier: License :: Other/Proprietary License
Classifier: Programming Language :: Python :: 3
Classifier: Programming Language :: Python :: 3.10
Classifier: Programming Language :: Python :: 3.11
Classifier: Programming Language :: Python :: 3.12
Requires-Dist: flwr (>=1.6.0,<2.0.0)
Requires-Dist: grpcio (>=1.60.0,<2.0.0)
